joblibs3/__init__.py
joblibs3/joblibs3.py
joblibs3-0.1.0.dist-info/METADATA
joblibs3-0.1.0.dist-info/RECORD
joblibs3-0.1.0.dist-info/WHEEL
joblibs3-0.1.0.dist-info/top_level.txt
