Metadata-Version: 2.1
Name: joblibs3
Version: 0.1.0
Summary: Python Package used to handle saving objects and Models on S3 Buckets
Home-page: https://github.com/rcourivaud/joblibs3
Author: Raphaël Courivaud
Author-email: r.courivaud@gmail.com
License: MIT license
Keywords: joblibs3
Platform: UNKNOWN
Classifier: Development Status :: 2 - Pre-Alpha
Classifier: Intended Audience :: Developers
Classifier: License :: OSI Approved :: MIT License
Classifier: Natural Language :: English
Classifier: Programming Language :: Python :: 3
Classifier: Programming Language :: Python :: 3.4
Classifier: Programming Language :: Python :: 3.5
Classifier: Programming Language :: Python :: 3.6
Requires-Dist: joblib
Requires-Dist: s3io
